{
  "version": 1,
  "note": "No secrets in repository. Fill keys via environment variables.",
  "servers": {
    "context7": {
      "enabled": true,
      "transport": "stdio",
      "command": "npx",
      "args": ["-y", "@upstash/context7-mcp"],
      "env": {
        "UPSTASH_CONTEXT7_API_KEY": "${UPSTASH_CONTEXT7_API_KEY}"
      }
    },
    "brave-search": {
      "enabled": false,
      "transport": "stdio",
      "command": "npx",
      "args": ["-y", "@modelcontextprotocol/server-brave-search"],
      "env": {
        "BRAVE_API_KEY": "${BRAVE_API_KEY}"
      }
    },
    "firecrawl": {
      "enabled": false,
      "transport": "stdio",
      "command": "npx",
      "args": ["-y", "firecrawl-mcp"],
      "env": {
        "FIRECRAWL_API_KEY": "${FIRECRAWL_API_KEY}"
      }
    },
    "github": {
      "enabled": false,
      "transport": "stdio",
      "command": "npx",
      "args": ["-y", "@modelcontextprotocol/server-github"],
      "env": {
        "GITHUB_PERSONAL_ACCESS_TOKEN": "${GITHUB_PERSONAL_ACCESS_TOKEN}"
      }
    }
  }
}
